capitalpayments/__init__.py
capitalpayments/capitalpaymentscore.py
capitalpayments/ipn.py
capitalpayments/url_manager.py
capitalpayments-0.1.4.dist-info/LICENSE
capitalpayments-0.1.4.dist-info/METADATA
capitalpayments-0.1.4.dist-info/WHEEL
capitalpayments-0.1.4.dist-info/top_level.txt
capitalpayments-0.1.4.dist-info/RECORD
