Metadata-Version: 2.1
Name: capitalpayments
Version: 0.1.4
Summary: For Api Capital Payments
Author: Javier (leqjl93)
Author-email: <javier.fernandez.pa93@gmail.com>
Keywords: python,capitalpayments,paymentprocessor,usdt.trc20
Classifier: Development Status :: 1 - Planning
Classifier: Intended Audience :: Developers
Classifier: Programming Language :: Python :: 3
Classifier: Operating System :: Unix
Classifier: Operating System :: MacOS :: MacOS X
Classifier: Operating System :: Microsoft :: Windows
License-File: LICENSE
Requires-Dist: requests
